watson/__init__.py
watson/cors/__init__.py
watson/cors/config.py
watson/cors/decorators.py
watson/cors/listeners.py
watson/cors/utils.py
watson_cors-1.0.0.dist-info/DESCRIPTION.rst
watson_cors-1.0.0.dist-info/METADATA
watson_cors-1.0.0.dist-info/RECORD
watson_cors-1.0.0.dist-info/WHEEL
watson_cors-1.0.0.dist-info/metadata.json
watson_cors-1.0.0.dist-info/top_level.txt
