Metadata-Version: 2.0
Name: watson-cors
Version: 1.0.0
Summary: CORS support for watson-framework.
Home-page: http://github.com/bespohk/watson-cors
Author: Simon Coulton
Author-email: simon@bespohk.com
License: Copyright (c) 2012-2014 Bespohk, and is maintained by multiple
Requires-Dist: watson-framework (>=3.5.2)
